flowhive_agent/__init__.py
flowhive_agent/cli/__init__.py
flowhive_agent/cli/flowhive.py
flowhive_agent/core/__init__.py
flowhive_agent/core/config.py
flowhive_agent/core/control_plane.py
flowhive_agent/core/crypto.py
flowhive_agent/core/exceptions.py
flowhive_agent/core/gpu_monitor.py
flowhive_agent/core/gpu_service.py
flowhive_agent/core/manager.py
flowhive_agent/core/models.py
flowhive_agent/core/runner.py
flowhive_agent/core/shell.py
flowhive_agent-0.2.0.dist-info/licenses/LICENSE
flowhive_agent-0.2.0.dist-info/METADATA
flowhive_agent-0.2.0.dist-info/WHEEL
flowhive_agent-0.2.0.dist-info/entry_points.txt
flowhive_agent-0.2.0.dist-info/top_level.txt
flowhive_agent-0.2.0.dist-info/RECORD
