Metadata-Version: 2.4
Name: flowhive-agent
Version: 0.2.0
Summary: FlowHive User Server Agent
Author-email: Dramwig <dramwig@gmail.com>
License-Expression: LicenseRef-FlowHive-Agent-NonCommercial-Copyleft-v1.0
Project-URL: Homepage, https://pypi.org/project/flowhive-agent/
Requires-Python: >=3.10
License-File: LICENSE
Requires-Dist: websockets>=14.0
Requires-Dist: psutil>=5.9.0
Requires-Dist: nvidia-ml-py>=12.535.0
Requires-Dist: tomli>=2.0.0; python_version < "3.11"
Dynamic: license-file
